README
setup.py
libzzzfs/__init__.py
libzzzfs/dataset.py
libzzzfs/interpreter.py
libzzzfs/util.py
libzzzfs/zfs.py
libzzzfs/zpool.py
libzzzfs/cmd/__init__.py
libzzzfs/cmd/zzzfs.py
libzzzfs/cmd/zzzpool.py
zzzfs.egg-info/PKG-INFO
zzzfs.egg-info/SOURCES.txt
zzzfs.egg-info/dependency_links.txt
zzzfs.egg-info/entry_points.txt
zzzfs.egg-info/top_level.txt