Metadata-Version: 1.1
Name: zzzfs
Version: 0.1.1
Summary: Dataset management à la ZFS
Home-page: https://github.com/steinbro/zzzfs
Author: Daniel W. Steinbrook
Author-email: steinbro@post.harvard.edu
License: CDDL
Keywords: zfs
Platform: UNKNOWN
Classifier: Development Status :: 3 - Alpha
Classifier: Intended Audience :: Developers
Classifier: Intended Audience :: System Administrators
Classifier: Operating System :: OS Independent
Classifier: Programming Language :: Python :: 2
Classifier: Programming Language :: Python :: 2.7
Classifier: Programming Language :: Python :: 3
Classifier: Programming Language :: Python :: 3.4
Classifier: Topic :: System :: Filesystems
